src/zina1_e-valente/__init__.py
src/zina1_e-valente/example.py
dns_eco-0.0.1.dist-info/METADATA
dns_eco-0.0.1.dist-info/WHEEL
dns_eco-0.0.1.dist-info/licenses/LICENSE
dns_eco-0.0.1.dist-info/RECORD
