Metadata-Version: 2.1
Name: dns-eco
Version: 0.0.1
Summary: DNS eco
Project-URL: Homepage, https://github.com/pypa/sampleproject
Project-URL: Bug Tracker, https://github.com/pypa/sampleproject/issues
Author-email: Emanuel valente <emanuel.valente@ifood.com.br>
License-File: LICENSE
Classifier: License :: OSI Approved :: MIT License
Classifier: Operating System :: OS Independent
Classifier: Programming Language :: Python :: 3
Requires-Python: >=3.7
